lifegu42d/__init__.py
lifegu42d/app/__init__.py
lifegu42d/app/lifegu42d_app.py
lifegu42d/lifegu42d.py
lifegu42d/main.py
lifegu42d/screens/__init__.py
lifegu42d/screens/chat_screen.py
lifegu42d/screens/logo_screen.py
lifegu42d/utils/__init__.py
lifegu42d/utils/classes/__init__.py
lifegu42d/utils/classes/chat.py
lifegu42d/utils/functions/__init__.py
lifegu42d/utils/functions/system.py
lifegu42d/widgets/__init__.py
lifegu42d/widgets/chat/__init__.py
lifegu42d/widgets/chat/chat_auth_form.py
lifegu42d/widgets/chat/chat_input.py
lifegu42d/widgets/chat/chat_input_markdown.py
lifegu42d/widgets/chat/chat_output_markdown.py
lifegu42d/widgets/chat/chat_window.py
lifegu42d/widgets/input/__init__.py
lifegu42d/widgets/input/labelled_input.py
lifegu42d-0.1.0.dist-info/LICENSE
lifegu42d-0.1.0.dist-info/METADATA
lifegu42d-0.1.0.dist-info/WHEEL
lifegu42d-0.1.0.dist-info/entry_points.txt
lifegu42d-0.1.0.dist-info/RECORD
